make2check/__init__.py
make2check/check_makefile_main.py
make2check-0.2.2.dist-info/LICENSE.txt
make2check-0.2.2.dist-info/METADATA
make2check-0.2.2.dist-info/WHEEL
make2check-0.2.2.dist-info/entry_points.txt
make2check-0.2.2.dist-info/top_level.txt
make2check-0.2.2.dist-info/RECORD
